logrich/__init__.py
logrich/app.py
logrich/app.pyi
logrich/config.py
logrich-1.0.10.dist-info/METADATA
logrich-1.0.10.dist-info/WHEEL
logrich-1.0.10.dist-info/top_level.txt
logrich-1.0.10.dist-info/RECORD
