Metadata-Version: 2.4
Name: logrich
Version: 1.0.10
Summary: log + rich = logrich
Author-email: Dmitry Mavlin <mavlind@list.ru>
License-Expression: MIT
Project-URL: Repository, https://gitflic.ru/project/mdv/logrich
Keywords: logger,rich,pretty
Requires-Python: >=3.10
Requires-Dist: rich>=12.4.4
